awslabs/mcp_lambda_handler/__init__.py
awslabs/mcp_lambda_handler/mcp_lambda_handler.py
awslabs/mcp_lambda_handler/session.py
awslabs/mcp_lambda_handler/types.py
awslabs_mcp_lambda_handler-0.1.12.dist-info/METADATA
awslabs_mcp_lambda_handler-0.1.12.dist-info/WHEEL
awslabs_mcp_lambda_handler-0.1.12.dist-info/entry_points.txt
awslabs_mcp_lambda_handler-0.1.12.dist-info/licenses/LICENSE
awslabs_mcp_lambda_handler-0.1.12.dist-info/licenses/NOTICE
awslabs_mcp_lambda_handler-0.1.12.dist-info/RECORD
