Metadata-Version: 2.4
Name: awslabs.mcp-lambda-handler
Version: 0.1.12
Summary: AWS Lambda MCP Server: A serverless HTTP handler for the Model Context Protocol (MCP) using AWS Lambda.
Project-URL: Homepage, https://awslabs.github.io/mcp/
Project-URL: Documentation, https://awslabs.github.io/mcp/servers/amazon_mq-mcp-server/
Project-URL: Source, https://github.com/awslabs/mcp.git
Project-URL: Bug Tracker, https://github.com/awslabs/mcp/issues
Project-URL: Changelog, https://github.com/awslabs/mcp/blob/main/src/amazon_mq-mcp-server/CHANGELOG.md
Author: Amazon Web Services
Author-email: Mike Chambers <mikegc@amazon.com>, AWSLabs MCP <203918161+awslabs-mcp@users.noreply.github.com>
License: Apache-2.0
License-File: LICENSE
License-File: NOTICE
Classifier: License :: OSI Approved :: Apache Software License
Classifier: Operating System :: OS Independent
Classifier: Programming Language :: Python
Classifier: Programming Language :: Python :: 3
Classifier: Programming Language :: Python :: 3.10
Classifier: Programming Language :: Python :: 3.11
Classifier: Programming Language :: Python :: 3.12
Classifier: Programming Language :: Python :: 3.13
Requires-Python: >=3.10
Requires-Dist: boto3>=1.38.1
Requires-Dist: botocore>=1.38.1
Requires-Dist: python-dateutil>=2.8.2
